buoyant/__init__.py
buoyant/buoy.py
buoyant/properties.py
buoyant/timezone.py
buoyant-0.7.0.dist-info/LICENSE
buoyant-0.7.0.dist-info/METADATA
buoyant-0.7.0.dist-info/WHEEL
buoyant-0.7.0.dist-info/top_level.txt
buoyant-0.7.0.dist-info/RECORD
