Metadata-Version: 2.1
Name: buoyant
Version: 0.7.0
Summary: Wrapper for the NOAA National Data Buoy Center
Home-page: https://github.com/fitnr/buoyant
Author: Neil Freeman
Author-email: contact@fakeisthenewreal.org
License: GPL
Platform: UNKNOWN
Classifier: License :: OSI Approved :: GNU General Public License v3 (GPLv3)
Classifier: Programming Language :: Python :: 3.6
Classifier: Programming Language :: Python :: 3.7
Classifier: Programming Language :: Python :: 3.8
Classifier: Topic :: Scientific/Engineering :: Atmospheric Science
Classifier: Intended Audience :: Science/Research
Requires-Python: >=3.5
Requires-Dist: requests (<3.0,>=2.4.1)
Requires-Dist: pytz (>=2015.6)
